README.txt
setup.cfg
setup.py
collective/__init__.py
collective.seeder.egg-info/PKG-INFO
collective.seeder.egg-info/SOURCES.txt
collective.seeder.egg-info/dependency_links.txt
collective.seeder.egg-info/entry_points.txt
collective.seeder.egg-info/namespace_packages.txt
collective.seeder.egg-info/not-zip-safe
collective.seeder.egg-info/requires.txt
collective.seeder.egg-info/top_level.txt
collective/seeder/__init__.py
collective/seeder/configure.zcml
collective/seeder/controlpanel.py
collective/seeder/interfaces.py
collective/seeder/subscribers.py
collective/seeder/tests.py
collective/seeder/profiles/default/controlpanel.xml
collective/seeder/profiles/default/metadata.xml
collective/seeder/profiles/default/registry.xml
docs/CONTRIBUTORS.txt
docs/HISTORY.txt
docs/INSTALL.txt
docs/LICENSE.GPL
docs/LICENSE.txt