Metadata-Version: 1.0
Name: collective.seeder
Version: 1.1
Summary: A torrent creation and seeding product for plone
Home-page: https://github.com/plumi/collective.seeder
Author: UNKNOWN
Author-email: UNKNOWN
License: GPL
Platform: UNKNOWN
Classifier: Framework :: Plone
Classifier: Programming Language :: Python
